MANIFEST.in
README.rst
setup.py
docs/HISTORY.txt
docs/LICENSE.GPL
docs/LICENSE.txt
ftw/__init__.py
ftw.meeting.egg-info/PKG-INFO
ftw.meeting.egg-info/SOURCES.txt
ftw.meeting.egg-info/dependency_links.txt
ftw.meeting.egg-info/entry_points.txt
ftw.meeting.egg-info/namespace_packages.txt
ftw.meeting.egg-info/not-zip-safe
ftw.meeting.egg-info/requires.txt
ftw.meeting.egg-info/top_level.txt
ftw/meeting/README.txt
ftw/meeting/__init__.py
ftw/meeting/attachment.py
ftw/meeting/config.py
ftw/meeting/configure.zcml
ftw/meeting/interfaces.py
ftw/meeting/lawgiver.zcml
ftw/meeting/setuphandlers.py
ftw/meeting/testing.py
ftw/meeting/utils.py
ftw/meeting/vocabularies.py
ftw/meeting/browser/__init__.py
ftw/meeting/browser/calendarsource.py
ftw/meeting/browser/configure.zcml
ftw/meeting/browser/create_meeting.py
ftw/meeting/browser/dndreorder.py
ftw/meeting/browser/export_ics.py
ftw/meeting/browser/interfaces.py
ftw/meeting/browser/meeting.pt
ftw/meeting/browser/meeting.py
ftw/meeting/browser/meetingitem.py
ftw/meeting/browser/preview.pt
ftw/meeting/browser/preview.py
ftw/meeting/browser/save_as_pdf.py
ftw/meeting/browser/scripts/meeting_toggle_date.js
ftw/meeting/browser/styles/arrow_down.png
ftw/meeting/browser/styles/arrow_right.png
ftw/meeting/browser/styles/meeting.css
ftw/meeting/content/__init__.py
ftw/meeting/content/configure.zcml
ftw/meeting/content/meeting.py
ftw/meeting/content/meetingitem.py
ftw/meeting/content/widget.py
ftw/meeting/latex/__init__.py
ftw/meeting/latex/configure.zcml
ftw/meeting/latex/layout.py
ftw/meeting/latex/tasklisting.py
ftw/meeting/latex/views.py
ftw/meeting/latex/workspace.py
ftw/meeting/latex/templates/events_listing.pt
ftw/meeting/latex/templates/layout.tex
ftw/meeting/latex/templates/meeting.tex
ftw/meeting/latex/templates/meetingitem.tex
ftw/meeting/latex/templates/tasklisting.tex
ftw/meeting/locales/ftw.meeting-manual.pot
ftw/meeting/locales/ftw.meeting.pot
ftw/meeting/locales/plone.pot
ftw/meeting/locales/de/LC_MESSAGES/ftw.meeting.po
ftw/meeting/locales/de/LC_MESSAGES/plone.po
ftw/meeting/locales/en/LC_MESSAGES/ftw.meeting.po
ftw/meeting/locales/fr/LC_MESSAGES/ftw.meeting.po
ftw/meeting/locales/fr/LC_MESSAGES/plone.po
ftw/meeting/profiles/default/browserlayer.xml
ftw/meeting/profiles/default/catalog.xml
